{
    "singleUrl": "https://github.com/Enalean/tuleap",
    "commits": [
        {
            "sha": "0843c046eee54b16ec6a7753c575838212770189",
            "is_vulnerable": false,
            "neutral": false
        },
        {
            "sha": "d6c837ed6fa66d319175954a42f93d4d86745208",
            "is_vulnerable": false,
            "neutral": false
        },
        {
            "sha": "326f3a3c44b0f2384bb45e275bc12c90aca3e709",
            "is_vulnerable": true,
            "neutral": false
        },
        {
            "sha": "bef9209f7f1df1c40adfd5deb70f617203d14927",
            "is_vulnerable": true,
            "neutral": false
        },
        {
            "sha": "6788e88843d3687fcb58c563113925c06ff8b069",
            "is_vulnerable": true,
            "neutral": false
        },
        {
            "sha": "45229d370d21c2bf730f12a83a3254ab649bd97e",
            "is_vulnerable": true,
            "neutral": false
        },
        {
            "sha": "d6b2f8b8c5098938bc094726a4826479ddbee941",
            "is_vulnerable": false,
            "neutral": false
        },
        {
            "sha": "1f47a5c8d3caaeeee3f096ee7a11165593499040",
            "is_vulnerable": true,
            "neutral": false
        },
        {
            "sha": "2b966daab755f2567f6a8f2c63618bb21270e5df",
            "is_vulnerable": true,
            "neutral": false
        },
        {
            "sha": "91535add59f4b3a04b6b8eab123c002cd5af180d",
            "is_vulnerable": false,
            "neutral": false
        },
        {
            "sha": "a8e6c00534e32b06ae9fe3b98605da6c7a78c84b",
            "is_vulnerable": true,
            "neutral": false
        },
        {
            "sha": "cbd096fffe39f32922fe706b80595048d7a027fd",
            "is_vulnerable": true,
            "neutral": false
        },
        {
            "sha": "ab12b686ced4cf233d3b15b08da008e0553eb6a6",
            "is_vulnerable": false,
            "neutral": false
        },
        {
            "sha": "4f39d660f530ad7c43e81de8675ffc74d003321c",
            "is_vulnerable": true,
            "neutral": false
        },
        {
            "sha": "1bdc6a787664a0597b5c64aa41ce45280d29093c",
            "is_vulnerable": true,
            "neutral": false
        },
        {
            "sha": "4d9a91a00b48216a02e80a8ec3501cea3c498a32",
            "is_vulnerable": true,
            "neutral": false
        },
        {
            "sha": "d78691f7eca72ab4cc7eb2b7447841d7a5488013",
            "is_vulnerable": true,
            "neutral": false
        },
        {
            "sha": "a5a7303f13d86fdac982969fe5ebaeb7293332f4",
            "is_vulnerable": true,
            "neutral": false
        },
        {
            "sha": "536ce6d74ee49fdf10e018207051d289d5bfc480",
            "is_vulnerable": true,
            "neutral": false
        },
        {
            "sha": "e0ac853ffc43b8cf6c3a3e800a2235ed4fffb1f4",
            "is_vulnerable": true,
            "neutral": false
        },
        {
            "sha": "ff75f2899c60a4546ee2d532e68a3febd07bdd14",
            "is_vulnerable": false,
            "neutral": false
        },
        {
            "sha": "293391d91c9e7f9f2f4c6629b3c72fc3eec6d805",
            "is_vulnerable": true,
            "neutral": false
        },
        {
            "sha": "787166ece4b9de1a0cc4343d1a174ad2c72ea62d",
            "is_vulnerable": true,
            "neutral": false
        },
        {
            "sha": "b7f1bc7dcc511eca7c61bab68af04a9cdf9ec7ac",
            "is_vulnerable": true,
            "neutral": false
        },
        {
            "sha": "bd47f29847fcd6a68d359bc8aefb8749bb8a1b7c",
            "is_vulnerable": false,
            "neutral": false
        },
        {
            "sha": "8a20a869e57b92d97e0b6f99b593e4c2541c3c5e",
            "is_vulnerable": true,
            "neutral": false
        },
        {
            "sha": "64e77561eba9f8233199c2962b3497ed7294a7d2",
            "is_vulnerable": false,
            "neutral": false
        },
        {
            "sha": "d413e13f223be8e416582b3d3e4f4efeb24a453f",
            "is_vulnerable": true,
            "neutral": false
        },
        {
            "sha": "b82be896b00a787ed46a77bd4700e8fccfe2e5ba",
            "is_vulnerable": false,
            "neutral": false
        },
        {
            "sha": "5fe3f3d960a70ae4a01a28f02d1e7c19481fa162",
            "is_vulnerable": true,
            "neutral": false
        },
        {
            "sha": "82f3687cb652613d8518256245557ec4a7886709",
            "is_vulnerable": true,
            "neutral": false
        },
        {
            "sha": "8e99e7c82d9fe569799019b9e1d614d38a184313",
            "is_vulnerable": false,
            "neutral": false
        },
        {
            "sha": "6466c17ffda941943fe0adfa306d8803104fc12b",
            "is_vulnerable": true,
            "neutral": false
        },
        {
            "sha": "3a5a179ea3a20cb2eac1a1aa9c1f583f67c555e2",
            "is_vulnerable": true,
            "neutral": false
        },
        {
            "sha": "7e221a9d1893c13407b35008762757a76d8e5654",
            "is_vulnerable": false,
            "neutral": false
        },
        {
            "sha": "cc38bcc59ce0c733ca915d95daec5f3082fb17ca",
            "is_vulnerable": false,
            "neutral": false
        },
        {
            "sha": "b91bcd57c8344ec2a4c1833629e400cef4dd901a",
            "is_vulnerable": false,
            "neutral": false
        },
        {
            "sha": "a14440f1d7921e00476749e6f6f65f3f8867e9f4",
            "is_vulnerable": true,
            "neutral": false
        },
        {
            "sha": "4c1ba07b33f77e815e11bcda272ee2ebcd668972",
            "is_vulnerable": true,
            "neutral": false
        },
        {
            "sha": "8c93d419e59e2cf19431095ad828ad9ae10450bb",
            "is_vulnerable": true,
            "neutral": false
        },
        {
            "sha": "2c50e75d8676fb44001712e446918f86d37c976a",
            "is_vulnerable": true,
            "neutral": false
        },
        {
            "sha": "13308818555ef36fc832ad3989323ebbf28073db",
            "is_vulnerable": true,
            "neutral": false
        },
        {
            "sha": "43676071bf28c759b48fa8e9da39126b947aaca0",
            "is_vulnerable": true,
            "neutral": false
        },
        {
            "sha": "304d880d32860346523026301b92e3694b34cc55",
            "is_vulnerable": true,
            "neutral": false
        },
        {
            "sha": "d0830760f56b5aa33dca2449a4245c1a027d2128",
            "is_vulnerable": true,
            "neutral": false
        },
        {
            "sha": "946ec6cabd13299c34bb617f71ab2a27ddf0f43a",
            "is_vulnerable": true,
            "neutral": false
        },
        {
            "sha": "7adb7b527f83557d3908488f607c14ed3bc6530c",
            "is_vulnerable": true,
            "neutral": false
        },
        {
            "sha": "f3d040fd3b05bb7de3e52c5a5b3b03a06e498d2e",
            "is_vulnerable": true,
            "neutral": false
        },
        {
            "sha": "0e60106c82e9f3b8bcae6108dafda62d468d8eff",
            "is_vulnerable": true,
            "neutral": false
        },
        {
            "sha": "2b9532f00742947733ceb24e19a244083e0a65ec",
            "is_vulnerable": true,
            "neutral": false
        },
        {
            "sha": "c947975a4f1ff7bbfd7d5cd24a2e16bf12bd96d4",
            "is_vulnerable": false,
            "neutral": false
        },
        {
            "sha": "20306caf470663e66bdaf689272eb50444f96ab2",
            "is_vulnerable": true,
            "neutral": false
        },
        {
            "sha": "8f0fa39906fbd04800449fd488ec73c987200278",
            "is_vulnerable": true,
            "neutral": false
        },
        {
            "sha": "58ecb1dee1c46075d3e089980301ebfbe0bafd33",
            "is_vulnerable": false,
            "neutral": false
        },
        {
            "sha": "33acc56f75d5a153b151b3d033451280c9b0c64a",
            "is_vulnerable": true,
            "neutral": false
        },
        {
            "sha": "a06cb42d55c840d61a484472ed6b169ab23853ac",
            "is_vulnerable": false,
            "neutral": false
        },
        {
            "sha": "2f5a5e80a1450355be7c0d5bf21932c49cf1350f",
            "is_vulnerable": true,
            "neutral": false
        },
        {
            "sha": "6105f464b2ffa32e9a24c0d6dded44f8a6bc8f7a",
            "is_vulnerable": true,
            "neutral": false
        },
        {
            "sha": "aacd5e798301f24f218298ec8236ec7bef0f5d52",
            "is_vulnerable": false,
            "neutral": false
        },
        {
            "sha": "e07be08c8d842d5924449340251bb8ff3ae2e22d",
            "is_vulnerable": true,
            "neutral": false
        },
        {
            "sha": "fdc93a736cbccad05de16ff0cc7cc3ef18dc93df",
            "is_vulnerable": false,
            "neutral": false
        },
        {
            "sha": "ba9762624424ff2c79e1740efb116bc0fb0dfbf3",
            "is_vulnerable": true,
            "neutral": false
        },
        {
            "sha": "3481076c4cc6b79c73ec0f55ae7f3cc0cb0e631e",
            "is_vulnerable": true,
            "neutral": false
        },
        {
            "sha": "6840529def97f564844e810e5a7c5bf837cf58d5",
            "is_vulnerable": false,
            "neutral": false
        },
        {
            "sha": "98db4c89aafbad25dfbd60c5fe581eb25d58a042",
            "is_vulnerable": true,
            "neutral": false
        },
        {
            "sha": "44bd460678ba0413599efc79061eaeb3e659e241",
            "is_vulnerable": true,
            "neutral": false
        },
        {
            "sha": "cd718845bb3441cd3f3288f359706714fe1feb08",
            "is_vulnerable": true,
            "neutral": false
        },
        {
            "sha": "7a8544134dd6c97c441758ad100907f3871d8e87",
            "is_vulnerable": true,
            "neutral": false
        },
        {
            "sha": "a15b808f108cfbcd16aa14c8d55d3db3cd7ac15c",
            "is_vulnerable": true,
            "neutral": false
        },
        {
            "sha": "0a11d36d7c340b63fdd7ab45f6ff261e4c58649c",
            "is_vulnerable": true,
            "neutral": false
        },
        {
            "sha": "a108186e7538676c4bf6e615f793f3b787a09b91",
            "is_vulnerable": false,
            "neutral": false
        },
        {
            "sha": "7da3037f24fdff2b041ae7b8e2def1033f779f46",
            "is_vulnerable": true,
            "neutral": false
        },
        {
            "sha": "15839cee347dadca83730ac31212b6806cfbef9d",
            "is_vulnerable": true,
            "neutral": false
        },
        {
            "sha": "b76c88ae05365d954009f5b26d44322a2a2fb095",
            "is_vulnerable": true,
            "neutral": false
        },
        {
            "sha": "7c45624c167ba92b86e0b7804adb0f35379a9722",
            "is_vulnerable": true,
            "neutral": false
        },
        {
            "sha": "6e93f43b503f1c6affc7a7efecbc8aa7d76f58a8",
            "is_vulnerable": true,
            "neutral": false
        },
        {
            "sha": "d6f6f8b962f735d2a6665b72f5d0bc22061abf79",
            "is_vulnerable": true,
            "neutral": false
        },
        {
            "sha": "5e97e2a5a3198286ba0c6418661d381711207a75",
            "is_vulnerable": true,
            "neutral": false
        },
        {
            "sha": "cd9e2cd46a2f322c1205bd5fa4f5df398e88ed8c",
            "is_vulnerable": true,
            "neutral": false
        },
        {
            "sha": "7fd21df287acf7494d39cd0058e0384908d8afb9",
            "is_vulnerable": true,
            "neutral": false
        },
        {
            "sha": "099dae8a94945f38e7baf52858aaa53312cc0a85",
            "is_vulnerable": true,
            "neutral": false
        },
        {
            "sha": "5ae4ee78be0e3c07b65ae8c6201335f90b23c2eb",
            "is_vulnerable": true,
            "neutral": false
        },
        {
            "sha": "2a0d9006aede32c4185874962e01e477101bfec1",
            "is_vulnerable": true,
            "neutral": false
        },
        {
            "sha": "1d08153d448ffb5bf46079b9e698461a12d06e38",
            "is_vulnerable": true,
            "neutral": false
        },
        {
            "sha": "1ed1b33ea54696a46eccfc349a761ea171a44f7d",
            "is_vulnerable": true,
            "neutral": false
        },
        {
            "sha": "2d51735aad74d06c7b4ed44995a337854ff52453",
            "is_vulnerable": true,
            "neutral": false
        },
        {
            "sha": "5a2c902509fc6b636a37f9c05c403b1802a27b8f",
            "is_vulnerable": true,
            "neutral": false
        },
        {
            "sha": "aebe23c317765e91aeb4d936e2242a6cb764d093",
            "is_vulnerable": true,
            "neutral": false
        },
        {
            "sha": "7a5cb2bcf1df0cc86ab2d1b33eeea2b61ea0903b",
            "is_vulnerable": true,
            "neutral": false
        },
        {
            "sha": "e5b82d9fc3aa14eef708f8665797992115916d83",
            "is_vulnerable": true,
            "neutral": false
        },
        {
            "sha": "ce56be4f49f5661f506e5a7baa8457421d52a828",
            "is_vulnerable": true,
            "neutral": false
        },
        {
            "sha": "3ae770b2a8ae4b84d9b3a87cb411746015c84635",
            "is_vulnerable": true,
            "neutral": false
        },
        {
            "sha": "fcf543ac9c6ec2e5ab8c0b2f9d5fc418119e406e",
            "is_vulnerable": true,
            "neutral": false
        },
        {
            "sha": "0d8dce966af3b085c1acfc8bb0e0fa3b105d047c",
            "is_vulnerable": true,
            "neutral": false
        },
        {
            "sha": "e779ba9b6336c791a21b4dc3167aa6e14b512af4",
            "is_vulnerable": true,
            "neutral": false
        },
        {
            "sha": "889774c6e631151ef9fec172b224139381b9affc",
            "is_vulnerable": true,
            "neutral": false
        },
        {
            "sha": "a7323bffecdbafbdf346dc9fec9192cb915e0a8e",
            "is_vulnerable": true,
            "neutral": false
        },
        {
            "sha": "0b2945fbd260d37aa0aff2ca1c867d160f76188d",
            "is_vulnerable": false,
            "neutral": false
        },
        {
            "sha": "214e64812ac8f8fc789ac4cf2c37fa3d5a0b8992",
            "is_vulnerable": true,
            "neutral": false
        },
        {
            "sha": "2bf37ff160e0f22c3c65c3464a0f6c1b0bc82748",
            "is_vulnerable": true,
            "neutral": false
        },
        {
            "sha": "73715dab99e71389bce86743ed6d3e6feef1cf8d",
            "is_vulnerable": true,
            "neutral": false
        },
        {
            "sha": "3723097807a8f69b16aae6123f3055b6b2343fd0",
            "is_vulnerable": true,
            "neutral": false
        },
        {
            "sha": "8a0c911d10496ef33c171b1b337977bfb8cfe8fa",
            "is_vulnerable": true,
            "neutral": false
        },
        {
            "sha": "8d1aea571246b837bf0649907b4f35f225230af9",
            "is_vulnerable": true,
            "neutral": false
        },
        {
            "sha": "91ee9de04ca1ffd0ec9446da165c7c5806601c48",
            "is_vulnerable": true,
            "neutral": false
        },
        {
            "sha": "ba49628f2efcd0d1ffe296cc0c82c939b36c92d9",
            "is_vulnerable": true,
            "neutral": false
        },
        {
            "sha": "d42da6e3c38c3f8f0fc777a39519be0f2c39047e",
            "is_vulnerable": true,
            "neutral": false
        },
        {
            "sha": "eaf5b3d95ae38a150b528efa5d792d3bf5edc57c",
            "is_vulnerable": true,
            "neutral": false
        },
        {
            "sha": "547980e97547de0076c36ebb439f23b4177d0d41",
            "is_vulnerable": true,
            "neutral": false
        },
        {
            "sha": "6b04dbf9a8c3d5c141c42e672e6b874bda9749b3",
            "is_vulnerable": true,
            "neutral": false
        },
        {
            "sha": "e12b019ae85e37ed586f9064fde0fa3669aa5409",
            "is_vulnerable": true,
            "neutral": false
        },
        {
            "sha": "c80a6ce2016a8fb26f476826506372ffa62970a8",
            "is_vulnerable": true,
            "neutral": false
        },
        {
            "sha": "307c1c8044522a2dcc711062b18a3b3f9059a6c3",
            "is_vulnerable": false,
            "neutral": false
        },
        {
            "sha": "24eaf5cd2b17611f001a63db4e62efd80a483e69",
            "is_vulnerable": true,
            "neutral": false
        },
        {
            "sha": "47d85e757c9e0f5530955a027e0839e475d9993d",
            "is_vulnerable": true,
            "neutral": false
        },
        {
            "sha": "2b3774bc9ef90c4ba132e14419baaabd6494bcc4",
            "is_vulnerable": true,
            "neutral": false
        },
        {
            "sha": "5cbbc02aec3b8d7edb53538f317d7c0092484d9e",
            "is_vulnerable": true,
            "neutral": false
        },
        {
            "sha": "b0364c312742f3e08880ad6d3c74cd0b4c6b9a51",
            "is_vulnerable": true,
            "neutral": false
        },
        {
            "sha": "93d10654b1d95c5bf500204666310418b01b8a8d",
            "is_vulnerable": false,
            "neutral": false
        },
        {
            "sha": "9965ae5061e0f3fcce152ab4b2b49e72cb089d00",
            "is_vulnerable": true,
            "neutral": false
        },
        {
            "sha": "edc3bcb52732f75fce37311b54199ab3c114878c",
            "is_vulnerable": true,
            "neutral": false
        },
        {
            "sha": "ea71ec7ee062aae8d1fa7a7325aaa759205c17d8",
            "is_vulnerable": false,
            "neutral": false
        },
        {
            "sha": "a4bf6f7913b3d6cb218059dd5204211b18feedab",
            "is_vulnerable": true,
            "neutral": false
        },
        {
            "sha": "e5303f008cda96c69913a577a1714bd827c0bdb7",
            "is_vulnerable": true,
            "neutral": false
        },
        {
            "sha": "746fc9f66b54220e5ab3eb5a98f27e35967534e9",
            "is_vulnerable": true,
            "neutral": false
        },
        {
            "sha": "c39d84b8fce92763c323ffac859f5f51c30f9f6b",
            "is_vulnerable": true,
            "neutral": false
        },
        {
            "sha": "cf8c18c08af72de8361ca1132d455b6783409389",
            "is_vulnerable": true,
            "neutral": false
        },
        {
            "sha": "4c39be9ae29b2479eb3e807f3dacb615e4e23080",
            "is_vulnerable": true,
            "neutral": false
        },
        {
            "sha": "7c7b590c80fd76360c558c43eba7e35a3bcf942d",
            "is_vulnerable": true,
            "neutral": false
        },
        {
            "sha": "0d13d67c7ba10c1d99be7cd877bcdf43f3570014",
            "is_vulnerable": false,
            "neutral": true
        },
        {
            "sha": "07b208d253be3341bfe5c3ee63dd21ca468f6d53",
            "is_vulnerable": false,
            "neutral": true
        },
        {
            "sha": "c1f847aa918b54e358f5a34047d666510b7e35e4",
            "is_vulnerable": false,
            "neutral": true
        },
        {
            "sha": "d02743e6ab53217d77687c66277d26bdbe37ca0f",
            "is_vulnerable": false,
            "neutral": true
        },
        {
            "sha": "dfeb53cffffc94bd1a91d5f4a8161937a6aea170",
            "is_vulnerable": false,
            "neutral": true
        },
        {
            "sha": "3cc5d3a116aa374b62107d70ee083994c3c9238f",
            "is_vulnerable": false,
            "neutral": true
        },
        {
            "sha": "8cb24e19203b7bf954b8678b9e359e7fde1d76a5",
            "is_vulnerable": false,
            "neutral": true
        },
        {
            "sha": "ade8c678d135ed1bab3d347cc6df1a2000cda1ce",
            "is_vulnerable": false,
            "neutral": true
        },
        {
            "sha": "84f46f37c61233db31f0cecf53e7528678e3b517",
            "is_vulnerable": false,
            "neutral": true
        },
        {
            "sha": "317398254afb0749753c73c9bdbf455ae0b500d0",
            "is_vulnerable": false,
            "neutral": true
        },
        {
            "sha": "3f892ec26d26930ee3b50a65ad94d89efbc7d26f",
            "is_vulnerable": false,
            "neutral": true
        },
        {
            "sha": "6b96e1e3b6a7143a0c71c84f28059699636ec7a6",
            "is_vulnerable": false,
            "neutral": true
        },
        {
            "sha": "c7d9e4ee7fabb5741b76a772f7c40ea3de6b2642",
            "is_vulnerable": false,
            "neutral": true
        },
        {
            "sha": "8432d4836e99f1837caaf6ed3d0cfe1ca0932024",
            "is_vulnerable": false,
            "neutral": true
        },
        {
            "sha": "e2a4cb339ac7a8c3685dbdad44ab9f5564eca040",
            "is_vulnerable": false,
            "neutral": true
        },
        {
            "sha": "293b97f8a43789b8895aa3af20557ec9abe68378",
            "is_vulnerable": false,
            "neutral": true
        },
        {
            "sha": "a6712bb87cf6eb5421df731b37a80d1c15e4b40b",
            "is_vulnerable": false,
            "neutral": true
        },
        {
            "sha": "e294f155c79f3fc130a753afaccda1cc01d7f870",
            "is_vulnerable": false,
            "neutral": true
        },
        {
            "sha": "50814a330068f27e7660d4d98f315a30c735ef8d",
            "is_vulnerable": false,
            "neutral": true
        },
        {
            "sha": "f4ac5ce92dc2010a352b378f118afa4ed1d01760",
            "is_vulnerable": false,
            "neutral": true
        },
        {
            "sha": "6817f4b22b7ff2e7ed1b48feed4f97f2124ccba9",
            "is_vulnerable": false,
            "neutral": true
        },
        {
            "sha": "e170accce11432e75ba3c628530777133eaef198",
            "is_vulnerable": false,
            "neutral": true
        },
        {
            "sha": "e2524041da7503115fa6899f5b5253289b682c50",
            "is_vulnerable": false,
            "neutral": true
        },
        {
            "sha": "6535d9b2f88fdadc512dee7d363d7a6881ae65e6",
            "is_vulnerable": false,
            "neutral": true
        },
        {
            "sha": "36a24a71df9088914fee867cf7eb91fde8bdcf1b",
            "is_vulnerable": false,
            "neutral": true
        },
        {
            "sha": "7bd524fe02ab0c1e764ff36bfe4aa832ab5f8f00",
            "is_vulnerable": false,
            "neutral": true
        },
        {
            "sha": "60f7ef71875bb41a5290898507f29cec96386eb2",
            "is_vulnerable": false,
            "neutral": true
        },
        {
            "sha": "71e833fa378111d66e363a6d0ddcc50dc8647d9e",
            "is_vulnerable": false,
            "neutral": true
        },
        {
            "sha": "d8d9d2e152d961203e4af38787d0a35c74afd534",
            "is_vulnerable": false,
            "neutral": true
        },
        {
            "sha": "2f351d52bf5b921d00d294612de4dc6be44c44a3",
            "is_vulnerable": false,
            "neutral": true
        },
        {
            "sha": "57d508c0ef028c55a4d2de679430b79fc80469bf",
            "is_vulnerable": false,
            "neutral": true
        },
        {
            "sha": "d5d8e4c06a3a706ce9e70c1130171263dd6b5fbd",
            "is_vulnerable": false,
            "neutral": true
        },
        {
            "sha": "1557005945d26c0c44ef7eb8d9abad15942356d3",
            "is_vulnerable": false,
            "neutral": true
        },
        {
            "sha": "69eb25375e0783fd6769f624f8e262e1dec4aabf",
            "is_vulnerable": false,
            "neutral": true
        },
        {
            "sha": "1c3539146a00b78843f5f999e264c04186c1e64f",
            "is_vulnerable": false,
            "neutral": true
        },
        {
            "sha": "777260f794372b8aec81b15217d7cbe6ed44313a",
            "is_vulnerable": false,
            "neutral": true
        },
        {
            "sha": "a65c8f871fd7c20c780846f0ea31a15779173947",
            "is_vulnerable": false,
            "neutral": true
        },
        {
            "sha": "6cb14ea94cf050e753be9b2033daf6d627340be2",
            "is_vulnerable": false,
            "neutral": true
        },
        {
            "sha": "2576226664405caadce9619e809ba1be0cde2686",
            "is_vulnerable": false,
            "neutral": true
        },
        {
            "sha": "da723d2991583c443e78a7ff0666aaeb4c7b9947",
            "is_vulnerable": false,
            "neutral": true
        },
        {
            "sha": "9a8c12559f54d899eba00c2369c16cb0d0792e8c",
            "is_vulnerable": false,
            "neutral": true
        },
        {
            "sha": "a30af981417b8dbe369734ac937fba102c77b6c3",
            "is_vulnerable": false,
            "neutral": true
        },
        {
            "sha": "c3c79749aa52afb5ff4aa66ea215ecce6beeb1b8",
            "is_vulnerable": false,
            "neutral": true
        },
        {
            "sha": "728a1be8fe7dc93f66b8e6aac0f9ede772ff975e",
            "is_vulnerable": false,
            "neutral": true
        },
        {
            "sha": "c0eff7d48675b0d333912dd7dbe0e3d5f96b4032",
            "is_vulnerable": false,
            "neutral": true
        },
        {
            "sha": "f8181be111c3b03e202d34b59c0401bffb28b9a8",
            "is_vulnerable": false,
            "neutral": true
        },
        {
            "sha": "80da61d69ba2c48c986a1edbabdc1ca1e9445ed2",
            "is_vulnerable": false,
            "neutral": true
        },
        {
            "sha": "382f2b0b91433e99ce74cb6fdb80bb5758960716",
            "is_vulnerable": false,
            "neutral": true
        },
        {
            "sha": "0ec3f9264406f691c70068cf328bf3aaba9f5275",
            "is_vulnerable": false,
            "neutral": true
        },
        {
            "sha": "759cede33b80c58e011d081e93ec6f0c2f698384",
            "is_vulnerable": false,
            "neutral": true
        },
        {
            "sha": "32aff7df84cb0cdf38b607d35018f4eaaf01bc4e",
            "is_vulnerable": false,
            "neutral": true
        },
        {
            "sha": "a12a559b0ea0fe90737dd61961c8a1c45a36c3b2",
            "is_vulnerable": false,
            "neutral": true
        },
        {
            "sha": "bb273bfa16ba5d3e9960b318e7e2fbd8853e0366",
            "is_vulnerable": false,
            "neutral": true
        },
        {
            "sha": "f44f4c32b6a6df11bdc820c0d1364b43d3d1cb92",
            "is_vulnerable": false,
            "neutral": true
        },
        {
            "sha": "464e6fab5f174bfd309f04c86ab94a08291036af",
            "is_vulnerable": false,
            "neutral": true
        },
        {
            "sha": "b77d07e44060e3ead3670590b2f3d00d210e97a9",
            "is_vulnerable": false,
            "neutral": true
        },
        {
            "sha": "f30c1a211d4ac582157e4f0cb4f38931a0514f1f",
            "is_vulnerable": false,
            "neutral": true
        },
        {
            "sha": "3548c1d207ac887026d61a7b00f5bc71ff57bd14",
            "is_vulnerable": false,
            "neutral": true
        },
        {
            "sha": "f1c2e6e139c1a71144d179209bea830799fc9a5f",
            "is_vulnerable": false,
            "neutral": true
        },
        {
            "sha": "c2be14b896bae375ad60e90a81f44496f970f0bb",
            "is_vulnerable": false,
            "neutral": true
        },
        {
            "sha": "71d51021e99b814af537a342a9c1a83b1bce6d5c",
            "is_vulnerable": false,
            "neutral": true
        },
        {
            "sha": "4f99d6704615f25ee870444eb42bcd96179f7fc6",
            "is_vulnerable": false,
            "neutral": true
        },
        {
            "sha": "91ce3de22ce5e1ae6f571a764726115bc29330de",
            "is_vulnerable": false,
            "neutral": true
        },
        {
            "sha": "d68698c526cc61188f192966432427a6847ca86a",
            "is_vulnerable": false,
            "neutral": true
        },
        {
            "sha": "0c2e998bf79b9f7ee32917dce0082d4d2daad53d",
            "is_vulnerable": false,
            "neutral": true
        },
        {
            "sha": "978be250f8a66fb0c03f23b8dddfe6bb2dfd5032",
            "is_vulnerable": false,
            "neutral": true
        },
        {
            "sha": "9bccae0b03c042ccbba17ac2395f88207a287d91",
            "is_vulnerable": false,
            "neutral": true
        },
        {
            "sha": "da170f9371cb7ae0e446a42692a11cf52f1a54dd",
            "is_vulnerable": false,
            "neutral": true
        },
        {
            "sha": "59be3e7e2c3f142b2c3221c1d910ff8761515dfb",
            "is_vulnerable": false,
            "neutral": true
        },
        {
            "sha": "438bc3c44042689fa6194b7e3df54b85859669ac",
            "is_vulnerable": false,
            "neutral": true
        },
        {
            "sha": "dbaae0eb648693b50739306ee46167dd9c68cf66",
            "is_vulnerable": false,
            "neutral": true
        },
        {
            "sha": "08a4599a0833220b63407de91a3be30c0fecf008",
            "is_vulnerable": false,
            "neutral": true
        },
        {
            "sha": "962bc70bac94c5a1cd8442869f047525f13e00b5",
            "is_vulnerable": false,
            "neutral": true
        },
        {
            "sha": "33f1b036e9bbfad21d42825b8887af486e6fe6e2",
            "is_vulnerable": false,
            "neutral": true
        },
        {
            "sha": "4762734ece939d172b44f5b1d9d77925f209b9b0",
            "is_vulnerable": false,
            "neutral": true
        },
        {
            "sha": "7e1828bbca2acdcbe43e6885e497ba3c1e4216cf",
            "is_vulnerable": false,
            "neutral": true
        },
        {
            "sha": "8a318739315297ae4a5376c438aa6fe08254cec5",
            "is_vulnerable": false,
            "neutral": true
        },
        {
            "sha": "0db9bd8d005072ed796ec515c43f8740550a0b27",
            "is_vulnerable": false,
            "neutral": true
        },
        {
            "sha": "dc74da384004c7e04026029e340de5993acde795",
            "is_vulnerable": false,
            "neutral": true
        },
        {
            "sha": "e312d271d86835819d7f02ddb9dc4b6f3cdd0095",
            "is_vulnerable": false,
            "neutral": true
        },
        {
            "sha": "757fe82613b6671f37e7610606781f75e57a96f3",
            "is_vulnerable": false,
            "neutral": true
        },
        {
            "sha": "2584e65ea2131901bab6704e97ada92ee8191514",
            "is_vulnerable": false,
            "neutral": true
        },
        {
            "sha": "203396f3f09348fd48ba7dcc61a1793237396e61",
            "is_vulnerable": false,
            "neutral": true
        },
        {
            "sha": "c4b57ff9987376685f3910c7a5052a3db607ffea",
            "is_vulnerable": false,
            "neutral": true
        },
        {
            "sha": "7db36303c634be836a1adc70514cafb9f0bd36ec",
            "is_vulnerable": false,
            "neutral": true
        },
        {
            "sha": "fb574d00c33bdf21c66ea596f7a796f30740901c",
            "is_vulnerable": false,
            "neutral": true
        },
        {
            "sha": "e5b95956eee6c8065064798f4aa080c106b3bf24",
            "is_vulnerable": false,
            "neutral": true
        },
        {
            "sha": "cc792f020ae1626d402a40f7d92fdd91306ac4d2",
            "is_vulnerable": false,
            "neutral": true
        },
        {
            "sha": "96fa06910da58ae24b7a5f90c9948efca0fcb324",
            "is_vulnerable": false,
            "neutral": true
        },
        {
            "sha": "15b458c99e941e246a9f88a02c7d4d9f0ca2ee0b",
            "is_vulnerable": false,
            "neutral": true
        },
        {
            "sha": "551d1d1d8dba735131d8c539f1dfd32e11978047",
            "is_vulnerable": false,
            "neutral": true
        },
        {
            "sha": "dddfc8c0edb2f6542f560d51707a1f0d40a1448f",
            "is_vulnerable": false,
            "neutral": true
        },
        {
            "sha": "3481a274c81b2c4cd1896285bdbcf52252c6650c",
            "is_vulnerable": false,
            "neutral": true
        },
        {
            "sha": "ffeb4bad990caf4fe01785182ddb502c9fd345f5",
            "is_vulnerable": false,
            "neutral": true
        },
        {
            "sha": "656347e703bb89e61d6125105ac9d9261e6c0b88",
            "is_vulnerable": false,
            "neutral": true
        },
        {
            "sha": "fdeb2fb8985aa0631e804a6bfde21481e5c52371",
            "is_vulnerable": false,
            "neutral": true
        },
        {
            "sha": "4f3faeb3463df4a96ceda4be62846471345e015d",
            "is_vulnerable": false,
            "neutral": true
        },
        {
            "sha": "e5ea83adae51fe42db0af0997c9af9e0e7f73af8",
            "is_vulnerable": false,
            "neutral": true
        },
        {
            "sha": "f125be487ba4c5e2cb7aa285bab63d1d2d2ed4ad",
            "is_vulnerable": false,
            "neutral": true
        },
        {
            "sha": "f56b87232e8fa7d2afa592150f8e209899cd95a7",
            "is_vulnerable": false,
            "neutral": true
        },
        {
            "sha": "e9840beeb6437404ebece710e61a91c76fee7841",
            "is_vulnerable": false,
            "neutral": true
        },
        {
            "sha": "1bee270da1ed5dc0f624e7e8e10c6c4af3ffb094",
            "is_vulnerable": false,
            "neutral": true
        },
        {
            "sha": "97403dff644e37e7f7623f4cd5289f6a1948b77b",
            "is_vulnerable": false,
            "neutral": true
        },
        {
            "sha": "58c8021fc1fb4fef0a63fc093bb834028d1aa4d1",
            "is_vulnerable": false,
            "neutral": true
        },
        {
            "sha": "5607ddc3f27d0d7898d18cb08fedaba2e84dae3b",
            "is_vulnerable": false,
            "neutral": true
        },
        {
            "sha": "f5b2e24ba6aa4c55d7243b09a59bd6749cb672ac",
            "is_vulnerable": false,
            "neutral": true
        },
        {
            "sha": "df78571f84df6e67663f5416f0b21e5d70b757d1",
            "is_vulnerable": false,
            "neutral": true
        },
        {
            "sha": "5d5de76b0187c2c950b16756606aabdddf42dde8",
            "is_vulnerable": false,
            "neutral": true
        },
        {
            "sha": "5ab877ff0b5afa2263f8cb0fc920156e34d51695",
            "is_vulnerable": false,
            "neutral": true
        },
        {
            "sha": "721c6aadb7009cd72f8a0b848e6679e889fad6ad",
            "is_vulnerable": false,
            "neutral": true
        },
        {
            "sha": "e3fa5b0e9b37ab9d5a56aabc19c5030e6e961315",
            "is_vulnerable": false,
            "neutral": true
        },
        {
            "sha": "114748ce85d71d2d056d75543213821c577e9e8e",
            "is_vulnerable": false,
            "neutral": true
        },
        {
            "sha": "f89bac12d961c89d00852c5c6657e4dd914ab171",
            "is_vulnerable": false,
            "neutral": true
        },
        {
            "sha": "1cce031a7302c81845dd7ed451c19b683aab2aab",
            "is_vulnerable": false,
            "neutral": true
        },
        {
            "sha": "f955c60e800d3561aa8e6cc66cfc684f8cdd6a09",
            "is_vulnerable": false,
            "neutral": true
        },
        {
            "sha": "604b7632e2a4621e206a4848ce550d0d773f98a4",
            "is_vulnerable": false,
            "neutral": true
        },
        {
            "sha": "b69565071c98118724afa18f0b63db3c25e6daca",
            "is_vulnerable": false,
            "neutral": true
        },
        {
            "sha": "ca5169fd8e2f18c0aedce4eb52271c782cead043",
            "is_vulnerable": false,
            "neutral": true
        },
        {
            "sha": "a2a2511f6d97536008701dddce63465da59a186c",
            "is_vulnerable": false,
            "neutral": true
        },
        {
            "sha": "dee604a8817f692c06ed1b12508262bce58a4917",
            "is_vulnerable": false,
            "neutral": true
        },
        {
            "sha": "6a9281b271a9ac00a38ad476a949ed4b69ea68dc",
            "is_vulnerable": false,
            "neutral": true
        },
        {
            "sha": "9c24e7e12e70faff5b0a22fa983254a5f7f94610",
            "is_vulnerable": false,
            "neutral": true
        },
        {
            "sha": "f1eeaa581feb438abd91b5dae2a596041dcc854b",
            "is_vulnerable": false,
            "neutral": true
        },
        {
            "sha": "22e04855b988fffef88f56fa5e4922762c04fcab",
            "is_vulnerable": false,
            "neutral": true
        },
        {
            "sha": "7d7bbcc441fa0b998d324e2bf5236a98b78ed3b8",
            "is_vulnerable": false,
            "neutral": true
        },
        {
            "sha": "24f0e864eded32c231ea030e7dd03017efc6e758",
            "is_vulnerable": false,
            "neutral": true
        },
        {
            "sha": "8acd3e412ae86201e445760147498cdc62f80559",
            "is_vulnerable": false,
            "neutral": true
        },
        {
            "sha": "cb9257d93fa8e5caab4b97976c579657e2a30d20",
            "is_vulnerable": false,
            "neutral": true
        },
        {
            "sha": "0e075f7352b76ff697a4f155ad2c075e8bcae179",
            "is_vulnerable": false,
            "neutral": true
        },
        {
            "sha": "a17e66e75f190db71f45097b019f8054dc037477",
            "is_vulnerable": false,
            "neutral": true
        },
        {
            "sha": "64035723c5485dff66f8c08dcf1dc73b64223d2e",
            "is_vulnerable": false,
            "neutral": true
        },
        {
            "sha": "9f71fdef35e72e673746ffe5d05142b75a1154eb",
            "is_vulnerable": false,
            "neutral": true
        },
        {
            "sha": "4f6c6143a68a33828e38d2ba4953e2570da040d8",
            "is_vulnerable": false,
            "neutral": true
        },
        {
            "sha": "9c1561cfd99dc7ad229244164eee2cf88df746db",
            "is_vulnerable": false,
            "neutral": true
        },
        {
            "sha": "d385556b9e84e5d63223e85bcdd62cdef570836d",
            "is_vulnerable": false,
            "neutral": true
        },
        {
            "sha": "986b09dbecb49ea50292970234b9a54d5e728c2e",
            "is_vulnerable": false,
            "neutral": true
        },
        {
            "sha": "fa87b0da1a699cfd12ecf70d887fbb0b1db28ece",
            "is_vulnerable": false,
            "neutral": true
        },
        {
            "sha": "d6ee17d9eae88f6445aea895a525269c2ad95d39",
            "is_vulnerable": false,
            "neutral": true
        },
        {
            "sha": "fcac07ed6df5f5779d36ce8cd561b57f359c58a2",
            "is_vulnerable": false,
            "neutral": true
        },
        {
            "sha": "c66767a29f9a405f9471f66ce460292ee074bc64",
            "is_vulnerable": false,
            "neutral": true
        },
        {
            "sha": "82d840ac313a30e59ad5d14cce5e6b846511f1c7",
            "is_vulnerable": false,
            "neutral": true
        },
        {
            "sha": "6c898b71bf28f65eeffc79ee9c26516c9af4ab2b",
            "is_vulnerable": false,
            "neutral": true
        },
        {
            "sha": "a673e8e9a621d73ee0b00c528c12355d6658a8e2",
            "is_vulnerable": false,
            "neutral": true
        },
        {
            "sha": "d8fbd461ba839d7f27cb2ae383497b2f66de3cb2",
            "is_vulnerable": false,
            "neutral": true
        },
        {
            "sha": "bbd66216292e9239479457bd4b9548106e35c7e0",
            "is_vulnerable": false,
            "neutral": true
        },
        {
            "sha": "79a4dfaabc5f7e4963ea3d896ad2738b985b7e3f",
            "is_vulnerable": false,
            "neutral": true
        },
        {
            "sha": "a092d1a121d570f38ace5ff678696b1bca6c8a7b",
            "is_vulnerable": false,
            "neutral": true
        },
        {
            "sha": "943b197bf9cfe4021654dcf79ce0c4d756faae8b",
            "is_vulnerable": false,
            "neutral": true
        },
        {
            "sha": "31210ed3f1169e246c1b5a201a1f6a4d5006218d",
            "is_vulnerable": false,
            "neutral": true
        },
        {
            "sha": "5aa76c053cad4d77cc2dfa07b1a793a67626b44e",
            "is_vulnerable": false,
            "neutral": true
        },
        {
            "sha": "89dd3367a40a204b116a8bbcb4e0d19dd6f02edf",
            "is_vulnerable": false,
            "neutral": true
        },
        {
            "sha": "44f90518f02e18db801ee0a62f8f7441ba1bcbf0",
            "is_vulnerable": false,
            "neutral": true
        },
        {
            "sha": "6b96f2d7f0b85dd27ab31fc5a131eac648da7a88",
            "is_vulnerable": false,
            "neutral": true
        },
        {
            "sha": "1fbd174457a531c52fefb7789e27362df2bbb289",
            "is_vulnerable": false,
            "neutral": true
        },
        {
            "sha": "a7908506e3f4b1e03556f5a60469eb402a610499",
            "is_vulnerable": false,
            "neutral": true
        },
        {
            "sha": "c858460e07290405525ce0056a01db50222c2d9d",
            "is_vulnerable": false,
            "neutral": true
        },
        {
            "sha": "4c377aff19032b33618935715f9c7d900d658480",
            "is_vulnerable": false,
            "neutral": true
        },
        {
            "sha": "889bb457823f1dffa7ba4b922953fc0c54b441ac",
            "is_vulnerable": false,
            "neutral": true
        },
        {
            "sha": "f731f204df1dbde34fc21f62f65676e7f76d89ab",
            "is_vulnerable": false,
            "neutral": true
        },
        {
            "sha": "bf868196703b38bdbb83afbdb67bd44e0c8388ef",
            "is_vulnerable": false,
            "neutral": true
        },
        {
            "sha": "708018eb7dc41b2d8f442dc3b6381d7e734d8be7",
            "is_vulnerable": false,
            "neutral": true
        },
        {
            "sha": "e8da2b2ccea519a0593d33f604f31037d805dc92",
            "is_vulnerable": false,
            "neutral": true
        },
        {
            "sha": "7ecd2ef846a605f28019280a265cd723d209105a",
            "is_vulnerable": false,
            "neutral": true
        },
        {
            "sha": "6e86d546f1c463d2ac56276544e101b3404fd3bb",
            "is_vulnerable": false,
            "neutral": true
        },
        {
            "sha": "8bc76160132c7cffcfaf635fa426b2f7b96ae5e4",
            "is_vulnerable": false,
            "neutral": true
        },
        {
            "sha": "446d27c545ed45e138157b784657a68cd59a883b",
            "is_vulnerable": false,
            "neutral": true
        },
        {
            "sha": "8022250a9987506bfde1ef5611cdef93ee51641a",
            "is_vulnerable": false,
            "neutral": true
        },
        {
            "sha": "2e93df1c8cbbfa7c5adcf8aeeed4aba521957b2c",
            "is_vulnerable": false,
            "neutral": true
        },
        {
            "sha": "1f4e2bba1fbb531f2ae2f5a10c0de71af2f28a3b",
            "is_vulnerable": false,
            "neutral": true
        },
        {
            "sha": "89e5503b3ddda2d8dd254834814f00cf288bff89",
            "is_vulnerable": false,
            "neutral": true
        },
        {
            "sha": "2080c519909adb4f9f234b8907efdcf55eed7fcf",
            "is_vulnerable": false,
            "neutral": true
        },
        {
            "sha": "6151fa2283235f7440a994326fc84f75be9cb0fe",
            "is_vulnerable": false,
            "neutral": true
        },
        {
            "sha": "ed90ab544251bbdc3c83dbd3c8d86c1a7928cd25",
            "is_vulnerable": false,
            "neutral": true
        },
        {
            "sha": "27a5b76e56ab809dbde9a2ec4af901037a470fac",
            "is_vulnerable": false,
            "neutral": true
        },
        {
            "sha": "ebae51f0e4ac20c65f819dd50e65b7976709e988",
            "is_vulnerable": false,
            "neutral": true
        },
        {
            "sha": "d2f708c591af15d0a9746c4c699bc0a47b0d0afa",
            "is_vulnerable": false,
            "neutral": true
        },
        {
            "sha": "72e6b9016d182d6e59ad08d3d767957e034f3d31",
            "is_vulnerable": false,
            "neutral": true
        },
        {
            "sha": "e35f0836e1cce9190cbbc622f9aba93aff4be1a8",
            "is_vulnerable": false,
            "neutral": true
        },
        {
            "sha": "3e17cdf326b4ba72fbcc3501376afd21e51a709a",
            "is_vulnerable": false,
            "neutral": true
        },
        {
            "sha": "f4fa728aeaeee27a11cf955714ccefcf8ec0c0b6",
            "is_vulnerable": false,
            "neutral": true
        },
        {
            "sha": "59816d5874203ca5d2da3155767f7327fd5635d1",
            "is_vulnerable": false,
            "neutral": true
        },
        {
            "sha": "a7b6add0fc5b2eb8aa7960fd7df1d9be49e1cc97",
            "is_vulnerable": false,
            "neutral": true
        },
        {
            "sha": "aee12a85531e125e7114dd4e51fa954f71dd6e93",
            "is_vulnerable": false,
            "neutral": true
        },
        {
            "sha": "70a0395d77bf9c7db478d3587b805cbf9a3bb1ce",
            "is_vulnerable": false,
            "neutral": true
        },
        {
            "sha": "822d3af02b3c6f015f0f76c0b58153c90ffba029",
            "is_vulnerable": false,
            "neutral": true
        },
        {
            "sha": "39ae475cf81df94f19dee6b0c9fe22cc172731d9",
            "is_vulnerable": false,
            "neutral": true
        },
        {
            "sha": "d06fddcf23795dcbda5ed1f91b031d746c516ee9",
            "is_vulnerable": false,
            "neutral": true
        },
        {
            "sha": "3122a69aef10dbe01462600b301f1c78fa80f289",
            "is_vulnerable": false,
            "neutral": true
        },
        {
            "sha": "eeb4b6633f31f18abb9065ae6491dffa0cba5a82",
            "is_vulnerable": false,
            "neutral": true
        },
        {
            "sha": "2dc73f9873e6f5e7ca69e7bbc1f35c5a26e3edf3",
            "is_vulnerable": false,
            "neutral": true
        },
        {
            "sha": "413e499af8d747ea157c227b92dc5d6a4403264e",
            "is_vulnerable": false,
            "neutral": true
        },
        {
            "sha": "ff5041aafb91913ad8eda65e8397755946af221e",
            "is_vulnerable": false,
            "neutral": true
        },
        {
            "sha": "f29c17ebde0bf3b29aaadd8230e4ef1ba2931b19",
            "is_vulnerable": false,
            "neutral": true
        },
        {
            "sha": "7c322fcc6a0b2422841e7d58583a90e65c974147",
            "is_vulnerable": false,
            "neutral": true
        },
        {
            "sha": "5cac42a6ce9ba36aa63d2d569d3f715f7d9d86db",
            "is_vulnerable": false,
            "neutral": true
        },
        {
            "sha": "7de59ea1119d3d1408c6cc10479901bf381f7b19",
            "is_vulnerable": false,
            "neutral": true
        },
        {
            "sha": "5872b949edf48e8696c04c15be96e8580e25e5eb",
            "is_vulnerable": false,
            "neutral": true
        },
        {
            "sha": "f5ac5e63a27590e2a05e327d6d9cde4a26599c25",
            "is_vulnerable": false,
            "neutral": true
        },
        {
            "sha": "fae3e115dcbdb7c6eb63a4787824c8597c636065",
            "is_vulnerable": false,
            "neutral": true
        },
        {
            "sha": "3d8a7cdbc75cc4fa3f76d2f7644ff589f8609ef1",
            "is_vulnerable": false,
            "neutral": true
        },
        {
            "sha": "dc6deed0ee01a4ac47c3c3baa36219ce3211940e",
            "is_vulnerable": false,
            "neutral": true
        },
        {
            "sha": "e01a583a73cda7bbe42cc9664b956d18baa26f87",
            "is_vulnerable": false,
            "neutral": true
        },
        {
            "sha": "26676b07ca741cf0bef9634c21bd0b767449a6aa",
            "is_vulnerable": false,
            "neutral": true
        },
        {
            "sha": "db044f6af5a13b43328cfe744a1eb08ff0627988",
            "is_vulnerable": false,
            "neutral": true
        },
        {
            "sha": "14f555c1a45f472829a03c9301a4d7c3754ae7f9",
            "is_vulnerable": false,
            "neutral": true
        },
        {
            "sha": "35171a5dfc5b7890b238b5eae9ae9fd745eaaa33",
            "is_vulnerable": false,
            "neutral": true
        },
        {
            "sha": "7f18becad82cb78415948ed945bbf3bc181597d8",
            "is_vulnerable": false,
            "neutral": true
        },
        {
            "sha": "dad500b03e841a56f5b3f3c1bbed3a8a72f38081",
            "is_vulnerable": false,
            "neutral": true
        },
        {
            "sha": "21faec53a26819e2515dcb03f67514efce7d4ca5",
            "is_vulnerable": false,
            "neutral": true
        },
        {
            "sha": "ffd36f770620517ce66524a0febef029b811468f",
            "is_vulnerable": false,
            "neutral": true
        },
        {
            "sha": "b22d4d2f9a6476fed30fa14226f0ec8be8c36a30",
            "is_vulnerable": false,
            "neutral": true
        },
        {
            "sha": "cc2d6f70080b906a36dc49f29a4c4bea7b1a2cb1",
            "is_vulnerable": false,
            "neutral": true
        },
        {
            "sha": "357373d58e47c0dd85f9648ec670ea8f27a1cdeb",
            "is_vulnerable": false,
            "neutral": true
        },
        {
            "sha": "55fac4772ef10ceda35d306c7e9ecf0804b186dd",
            "is_vulnerable": false,
            "neutral": true
        },
        {
            "sha": "511a27fb042c87d7f169739b2c16799a8e3f6806",
            "is_vulnerable": false,
            "neutral": true
        },
        {
            "sha": "35c800f47874b47956f1f431b21efb81d204609f",
            "is_vulnerable": false,
            "neutral": true
        },
        {
            "sha": "9b1f73466bb4d6f51d85cbc8dddf2159b470442f",
            "is_vulnerable": false,
            "neutral": true
        },
        {
            "sha": "b1ae0961f12e556215ccf1b4d0ec855b450925d1",
            "is_vulnerable": false,
            "neutral": true
        },
        {
            "sha": "252b02fe0a88df39458f71e0d5f92081053071db",
            "is_vulnerable": false,
            "neutral": true
        },
        {
            "sha": "74ff3e1171d38af2c0637d9ddf43221679e397d9",
            "is_vulnerable": false,
            "neutral": true
        },
        {
            "sha": "98746b82106379ae3a202a6d992489daefde493e",
            "is_vulnerable": false,
            "neutral": true
        },
        {
            "sha": "93a4106db8d45c6d3c5bb20891b489ed8febdfe6",
            "is_vulnerable": false,
            "neutral": true
        },
        {
            "sha": "d8cbf17412d3f9bea136df056b88df5f821b691e",
            "is_vulnerable": false,
            "neutral": true
        },
        {
            "sha": "6efb0715dc933a6f51768da860de686416c0ec94",
            "is_vulnerable": false,
            "neutral": true
        },
        {
            "sha": "656e5c407d9458f6906d1d3c41e5f7eb9abc3940",
            "is_vulnerable": false,
            "neutral": true
        },
        {
            "sha": "860761611777d3cdf8e76d08aac0a82c05582949",
            "is_vulnerable": false,
            "neutral": true
        },
        {
            "sha": "8f5dc1b4b093d8e22bdc7a23e76c2be03b6f9e20",
            "is_vulnerable": false,
            "neutral": true
        },
        {
            "sha": "e469eb78a8ee5d1dfcbc34fd306ed187bffd9210",
            "is_vulnerable": false,
            "neutral": true
        },
        {
            "sha": "03bbdced0105c26f562b5fb7facc9cdaae3fd305",
            "is_vulnerable": false,
            "neutral": true
        },
        {
            "sha": "34987416944ab53f8c85b04b80e2472cd67cc7d2",
            "is_vulnerable": false,
            "neutral": true
        },
        {
            "sha": "213ae697b28ab29ba862f2976aaa53018a323d42",
            "is_vulnerable": false,
            "neutral": true
        },
        {
            "sha": "843da3bb0f63adeaa03ed491ec48158df16fc047",
            "is_vulnerable": false,
            "neutral": true
        },
        {
            "sha": "b6d770662513c8a44c48dd963a2188c76fa90d49",
            "is_vulnerable": false,
            "neutral": true
        },
        {
            "sha": "fc8f2a8cc553feffd5c8d9e20edb5f87d5f66ce2",
            "is_vulnerable": false,
            "neutral": true
        },
        {
            "sha": "8192f3e82e205d2344ae91ed3ae37a8114767414",
            "is_vulnerable": false,
            "neutral": true
        },
        {
            "sha": "9919aaaa53ce960070f3983dab251384bf2d2e89",
            "is_vulnerable": false,
            "neutral": true
        },
        {
            "sha": "7aa57b173b2ec6ce8655dc7bbdaa7721d41ee93f",
            "is_vulnerable": false,
            "neutral": true
        },
        {
            "sha": "a230095cbad91f1f76fd26c134067d713a8452a1",
            "is_vulnerable": false,
            "neutral": true
        },
        {
            "sha": "a1d93382dc31b83fc19460526e7baf885f19de9f",
            "is_vulnerable": false,
            "neutral": true
        },
        {
            "sha": "f918e507982296429b79729ab781d874ae3c9b7d",
            "is_vulnerable": false,
            "neutral": true
        },
        {
            "sha": "689e280ac58e29a5cd53518ea37181119d2c697e",
            "is_vulnerable": false,
            "neutral": true
        },
        {
            "sha": "2a0f682a776d4246350cd7de1905a4e348dd7a53",
            "is_vulnerable": false,
            "neutral": true
        },
        {
            "sha": "68cbc2910450501e08c4e8dff259017da3a52b20",
            "is_vulnerable": false,
            "neutral": true
        },
        {
            "sha": "79a35ea3ac38fda6c2898843ca4a5d36472eb533",
            "is_vulnerable": false,
            "neutral": true
        },
        {
            "sha": "d4070d30c23b1b022bf21ba70ae098744270410f",
            "is_vulnerable": false,
            "neutral": true
        },
        {
            "sha": "173de6bedc44cd545e39c38d5dbf15ea02fc0a14",
            "is_vulnerable": false,
            "neutral": true
        },
        {
            "sha": "60c4eb25095cc43d22f74e5ac09102c38c74ed14",
            "is_vulnerable": false,
            "neutral": true
        },
        {
            "sha": "0a2aa884dec57901f3e62320a81bdbe831428101",
            "is_vulnerable": false,
            "neutral": true
        },
        {
            "sha": "31613776c2b9e9e364614450b81e5ff9372d2293",
            "is_vulnerable": false,
            "neutral": true
        },
        {
            "sha": "44d2ae8afaa07191ce89bcb67c272db9159c6855",
            "is_vulnerable": false,
            "neutral": true
        },
        {
            "sha": "20d66587d51f88fb568a3c64efbb3de446f51f83",
            "is_vulnerable": false,
            "neutral": true
        },
        {
            "sha": "3d566fb2b3d8436597125d259785ba3dc8385649",
            "is_vulnerable": false,
            "neutral": true
        },
        {
            "sha": "bd501340668be4b70ba926b9114d276463341d63",
            "is_vulnerable": false,
            "neutral": true
        },
        {
            "sha": "821aa1eb579fec1f66b11b1c3e36e589fc8e5666",
            "is_vulnerable": false,
            "neutral": true
        },
        {
            "sha": "5f0af6e94b6274de3dc9d5d26683e048b650bd48",
            "is_vulnerable": false,
            "neutral": true
        },
        {
            "sha": "9604901ea9e81ca654325fcf4ecd2f0fe53f0d69",
            "is_vulnerable": false,
            "neutral": true
        },
        {
            "sha": "27a67d83218dee59765b0c3df9f3347f7d2a353a",
            "is_vulnerable": false,
            "neutral": true
        },
        {
            "sha": "55f5ecc03382491c280d07e98267c971d2e23168",
            "is_vulnerable": false,
            "neutral": true
        },
        {
            "sha": "ed0bdecd906e2cd1f7fc9b6b99a4c0118daec1b6",
            "is_vulnerable": false,
            "neutral": true
        },
        {
            "sha": "577c850adea6f887e26cb1236f083c956e612de4",
            "is_vulnerable": false,
            "neutral": true
        },
        {
            "sha": "35fa71595c0dcdcf13a3c4979a3df949af015497",
            "is_vulnerable": false,
            "neutral": true
        },
        {
            "sha": "1b1815b51c944d65fdcc139032026efd26339bfe",
            "is_vulnerable": false,
            "neutral": true
        },
        {
            "sha": "e0e4a18309d5acdb4b1c3b82263f7a288749d3e4",
            "is_vulnerable": false,
            "neutral": true
        },
        {
            "sha": "a88007894929670134c20949e7462533de08e467",
            "is_vulnerable": false,
            "neutral": true
        },
        {
            "sha": "6490a6a5bfa99cf9d5b4cf017747c04830a34d2d",
            "is_vulnerable": false,
            "neutral": true
        },
        {
            "sha": "04b9a4d76211cd9decdefca325f1945f98a4ba82",
            "is_vulnerable": false,
            "neutral": true
        },
        {
            "sha": "ff04161b99aae98e5b9dabf3b4cb00cbbe3413b1",
            "is_vulnerable": false,
            "neutral": true
        },
        {
            "sha": "3b2ab5c9b209a9fa5fde5c25db79c8072f829699",
            "is_vulnerable": false,
            "neutral": true
        },
        {
            "sha": "1fd3475e6bf78e792a23df3c6aff29ccd321ab18",
            "is_vulnerable": false,
            "neutral": true
        },
        {
            "sha": "58758bfe10750d131d07a22d52b11c9e299ddc28",
            "is_vulnerable": false,
            "neutral": true
        },
        {
            "sha": "563a7c9c140e026ba1afa9023f474cf57df0dad6",
            "is_vulnerable": false,
            "neutral": true
        },
        {
            "sha": "720db811258a7ac46d5656bd30584f5fba7a69c3",
            "is_vulnerable": false,
            "neutral": true
        },
        {
            "sha": "a058c82a387529e304e5f8c6faf4905ebfad515b",
            "is_vulnerable": false,
            "neutral": true
        },
        {
            "sha": "d6185f25fcb5f7c8d6d81b362fc3f2bff83df645",
            "is_vulnerable": false,
            "neutral": true
        },
        {
            "sha": "f9f196f304cd4a0ac060eb7539c1fa601968035f",
            "is_vulnerable": false,
            "neutral": true
        },
        {
            "sha": "4d27eff7598419affd5f248a059fb6b31852a41e",
            "is_vulnerable": false,
            "neutral": true
        },
        {
            "sha": "6466c17ffda941943fe0adfa306d8803104fc12b",
            "is_vulnerable": false,
            "neutral": true
        },
        {
            "sha": "113a548f4ccf613446d7469e67396a5a27407355",
            "is_vulnerable": false,
            "neutral": true
        },
        {
            "sha": "e552d3ba7286b4a69cc5933f2ba709b2eb8c8235",
            "is_vulnerable": false,
            "neutral": true
        },
        {
            "sha": "4f84e34c73fe80686315851a1e05f5c74ce3e06d",
            "is_vulnerable": false,
            "neutral": true
        },
        {
            "sha": "d1f549f911664bd040ec2f18c291c8d0f3ddfb9b",
            "is_vulnerable": false,
            "neutral": true
        },
        {
            "sha": "54df86d105c5eb869ab01da61d727a7a256abcf0",
            "is_vulnerable": false,
            "neutral": true
        },
        {
            "sha": "825fe990ea41234256ad8c82d5f81d3559920b66",
            "is_vulnerable": false,
            "neutral": true
        },
        {
            "sha": "decc93081f67d13c7c60b2b6a01f9ec1cf995383",
            "is_vulnerable": false,
            "neutral": true
        },
        {
            "sha": "5b9161578c61cf541a458bfdc55e8533aadcfbe4",
            "is_vulnerable": false,
            "neutral": true
        },
        {
            "sha": "a9fbd3f128efa3d82259d362790b5ad22fb88d2b",
            "is_vulnerable": false,
            "neutral": true
        },
        {
            "sha": "9fa5c1dbe87b1ca1cb02b43f0f6c07d52b08a74f",
            "is_vulnerable": false,
            "neutral": true
        },
        {
            "sha": "f8418f320faa43004b128ed06ab12947c244e96f",
            "is_vulnerable": false,
            "neutral": true
        },
        {
            "sha": "62ee2e36c44e21fada37d1e49c766a10135f6bc2",
            "is_vulnerable": false,
            "neutral": true
        },
        {
            "sha": "8b435083972cc8a8cba188b1c665aa00af0e997f",
            "is_vulnerable": false,
            "neutral": true
        },
        {
            "sha": "67458778db0ab366856b90a9bce7404f061691f3",
            "is_vulnerable": false,
            "neutral": true
        },
        {
            "sha": "3ed832d13f94914c9eccee4309017e528dfe9ee8",
            "is_vulnerable": false,
            "neutral": true
        },
        {
            "sha": "59eab5283720a19c07e427dbc704f5f296fb336d",
            "is_vulnerable": false,
            "neutral": true
        },
        {
            "sha": "3d8220c9c1f669db47157ad52a00ed096f443436",
            "is_vulnerable": false,
            "neutral": true
        },
        {
            "sha": "a9b33d07593e8bc8e8baa51d5587f1a70770c4b9",
            "is_vulnerable": false,
            "neutral": true
        },
        {
            "sha": "b6a7172e87f39e78758261a7a9ce4dd0b3af2bdd",
            "is_vulnerable": false,
            "neutral": true
        },
        {
            "sha": "4b3b7a37896154cd18139804ce784600589b8931",
            "is_vulnerable": false,
            "neutral": true
        },
        {
            "sha": "33289df3788babb5b31fd031601c34c5ad9ba574",
            "is_vulnerable": false,
            "neutral": true
        },
        {
            "sha": "a7053ae4c46b82339d840f75ed803a5794fa712c",
            "is_vulnerable": false,
            "neutral": true
        },
        {
            "sha": "35fcdb5c0bfb25473adad6131f8fb8b93eb301d8",
            "is_vulnerable": false,
            "neutral": true
        },
        {
            "sha": "b67c2e7c191af85b261aaa800729dededfd524e9",
            "is_vulnerable": false,
            "neutral": true
        },
        {
            "sha": "abb4e213dc81080b0453f864baafac2268161b5f",
            "is_vulnerable": false,
            "neutral": true
        },
        {
            "sha": "f82b04639faabc5aefe5bb93b347eafe0f474e63",
            "is_vulnerable": false,
            "neutral": true
        },
        {
            "sha": "e0f7f38065ae1dc29f65b0225673e6b4772bfdda",
            "is_vulnerable": false,
            "neutral": true
        },
        {
            "sha": "325f5ae0bd410255d37e9dfe0d98910f48ac2088",
            "is_vulnerable": false,
            "neutral": true
        },
        {
            "sha": "95fa7c7a3243787e012ffb8352502111e5089e1c",
            "is_vulnerable": false,
            "neutral": true
        },
        {
            "sha": "bb09b85a12bb08c189868b6f7516b7bf400e28b9",
            "is_vulnerable": false,
            "neutral": true
        },
        {
            "sha": "7b8f3f2d5faa449e9b15006c46c308b86a3583b6",
            "is_vulnerable": false,
            "neutral": true
        },
        {
            "sha": "3999d9a051a1afb4934ede360f9c144ef89b7a8f",
            "is_vulnerable": false,
            "neutral": true
        },
        {
            "sha": "377b7db649126e5f5fb1d00e7333863618ddd147",
            "is_vulnerable": false,
            "neutral": true
        },
        {
            "sha": "4ede00e103828e7396e014ae1adb612bc4e63738",
            "is_vulnerable": false,
            "neutral": true
        },
        {
            "sha": "9baa6ed427bada0eb8bb24f0abd2aa10733da418",
            "is_vulnerable": false,
            "neutral": true
        },
        {
            "sha": "011f582c5b923593fcd3d15ece1d7cde36ffd693",
            "is_vulnerable": false,
            "neutral": true
        },
        {
            "sha": "acedcbefc4d9efff18479a6af4f7d2bc95ae14bb",
            "is_vulnerable": false,
            "neutral": true
        },
        {
            "sha": "b9878725a32fc1db5a0700b3d66d1fc0675d1106",
            "is_vulnerable": false,
            "neutral": true
        }
    ]
}